medialog.leadimagesize-0.5-py2.7-nspkg.pth
medialog/.DS_Store
medialog/leadimagesize/.DS_Store
medialog/leadimagesize/__init__.py
medialog/leadimagesize/behavior.py
medialog/leadimagesize/behaviors.zcml
medialog/leadimagesize/configure.zcml
medialog/leadimagesize/interfaces.py
medialog/leadimagesize/profiles.zcml
medialog/leadimagesize/setuphandlers.py
medialog/leadimagesize/vocabulary.py
medialog/leadimagesize/browser/__init__.py
medialog/leadimagesize/browser/collection-summary_view.pt
medialog/leadimagesize/browser/configure.zcml
medialog/leadimagesize/browser/container-folder_summary_view.pt
medialog/leadimagesize/browser/listing_album.pt
medialog/leadimagesize/browser/newsitem.pt
medialog/leadimagesize/browser/newsitem.py
medialog/leadimagesize/browser/sizedleadimage.pt
medialog/leadimagesize/browser/sizedleadimage.py
medialog/leadimagesize/browser/views.py
medialog/leadimagesize/portlets/__init__.py
medialog/leadimagesize/portlets/configure.zcml
medialog/leadimagesize/portlets/leadimage.pt
medialog/leadimagesize/portlets/leadimage.py
medialog/leadimagesize/profiles/.DS_Store
medialog/leadimagesize/profiles/default/browserlayer.xml
medialog/leadimagesize/profiles/default/metadata.xml
medialog/leadimagesize/profiles/default/portlets.xml
medialog/leadimagesize/profiles/default/registry.xml
medialog/leadimagesize/profiles/uninstall/browserlayer.xml
medialog/leadimagesize/profiles/uninstall/registry.xml
medialog.leadimagesize-0.5.dist-info/METADATA
medialog.leadimagesize-0.5.dist-info/RECORD
medialog.leadimagesize-0.5.dist-info/WHEEL
medialog.leadimagesize-0.5.dist-info/entry_points.txt
medialog.leadimagesize-0.5.dist-info/namespace_packages.txt
medialog.leadimagesize-0.5.dist-info/top_level.txt
